crawl_toolkit/__init__.py
crawl_toolkit/crawl_toolkit.py
crawl_toolkit/enum/__init__.py
crawl_toolkit/enum/fetch_type.py
crawl_toolkit/enum/language.py
crawl_toolkit/prompts/__init__.py
crawl_toolkit/prompts/extract_keyword_connections_system.txt
crawl_toolkit/prompts/get_keywords_3.txt
crawl_toolkit/prompts/keyword_analysis_prompt.py
crawl_toolkit/service/__init__.py
crawl_toolkit/service/brightdata_service.py
crawl_toolkit/service/content_cleaner.py
crawl_toolkit/service/openai_service.py
crawl_toolkit/service/openrouter_service.py
crawl_toolkit/service/content_cleaner/__init__.py
crawl_toolkit/service/content_cleaner/abstract_cleaner.py
crawl_toolkit/service/content_cleaner/content_cleaner_factory.py
crawl_toolkit/service/content_cleaner/crawl4ai_cleaner.py
crawl_toolkit/service/content_cleaner/factory.py
crawl_toolkit/service/content_cleaner/html_cleaner.py
crawl_toolkit/service/content_cleaner/markdown_cleaner.py
crawl_toolkit-0.1.3.dist-info/METADATA
crawl_toolkit-0.1.3.dist-info/WHEEL
crawl_toolkit-0.1.3.dist-info/RECORD
