Metadata-Version: 2.4
Name: crawl-toolkit
Version: 0.1.3
Summary: Narzędzie do crawlowania i analizy treści
Project-URL: Homepage, https://github.com/patryk/crawl-toolkit
Project-URL: Bug Tracker, https://github.com/patryk/crawl-toolkit/issues
Author-email: Patryk <patryk@example.com>
Classifier: License :: OSI Approved :: MIT License
Classifier: Operating System :: OS Independent
Classifier: Programming Language :: Python :: 3
Requires-Python: >=3.8
Requires-Dist: aiohttp>=3.8.0
Requires-Dist: beautifulsoup4>=4.9.3
Requires-Dist: openai>=1.0.0
Requires-Dist: pydantic>=2.0.0
Provides-Extra: dev
Requires-Dist: black>=24.1.0; extra == 'dev'
Requires-Dist: isort>=5.13.0; extra == 'dev'
Requires-Dist: mypy>=1.8.0; extra == 'dev'
Requires-Dist: pytest-asyncio>=0.23.0; extra == 'dev'
Requires-Dist: pytest>=8.0.0; extra == 'dev'
